{
  "timestamp": "2026-02-08T02:15:43.665067",
  "total_tests": 8,
  "passed": 5,
  "failed": 3,
  "tests": [
    {
      "name": "test_username_enumeration",
      "full_name": "tests/authentication/test_01_username_enumeration.py::test_username_enumeration",
      "outcome": "passed",
      "duration": 95.91437625999998,
      "cvss_score": 9.1
    },
    {
      "name": "test_credential_guessing",
      "full_name": "tests/authentication/test_02_credential_guessing.py::test_credential_guessing",
      "outcome": "passed",
      "duration": 93.67494805700002,
      "cvss_score": 9.1
    },
    {
      "name": "test_password_attack_6",
      "full_name": "tests/authentication/test_03_password_attack_6_attempts.py::test_password_attack_6",
      "outcome": "passed",
      "duration": 60.94133873800001,
      "cvss_score": 7.4
    },
    {
      "name": "test_password_attack_7",
      "full_name": "tests/authentication/test_04_password_attack_7_attempts.py::test_password_attack_7",
      "outcome": "passed",
      "duration": 69.07405012099997,
      "cvss_score": 7.4
    },
    {
      "name": "test_password_attack_8",
      "full_name": "tests/authentication/test_05_password_attack_8_attempts.py::test_password_attack_8",
      "outcome": "passed",
      "duration": 77.25703420500002,
      "cvss_score": 7.4
    },
    {
      "name": "test_session_hijacking",
      "full_name": "tests/session_management/test_01_session_hijacking.py::test_session_hijacking",
      "outcome": "failed",
      "duration": 8.811476686999981,
      "cvss_score": null
    },
    {
      "name": "test_idle_timeout",
      "full_name": "tests/session_management/test_02_idle_timeout.py::test_idle_timeout",
      "outcome": "failed",
      "duration": 8.80220040200004,
      "cvss_score": null
    },
    {
      "name": "test_expired_session_reuse",
      "full_name": "tests/session_management/test_03_expired_session_reuse.py::test_expired_session_reuse",
      "outcome": "failed",
      "duration": 8.823049739999988,
      "cvss_score": null
    }
  ]
}